pymic/__init__.py
pymic/io/__init__.py
pymic/io/h5_dataset.py
pymic/io/image_read_write.py
pymic/io/nifty_dataset.py
pymic/layer/__init__.py
pymic/layer/activation.py
pymic/layer/convolution.py
pymic/layer/deconvolution.py
pymic/layer/space2channel.py
pymic/loss/__init__.py
pymic/loss/loss_dict_cls.py
pymic/loss/loss_dict_seg.py
pymic/loss/cls/__init__.py
pymic/loss/cls/basic.py
pymic/loss/cls/infoNCE.py
pymic/loss/cls/util.py
pymic/loss/seg/__init__.py
pymic/loss/seg/abstract.py
pymic/loss/seg/ars_tversky.py
pymic/loss/seg/ce.py
pymic/loss/seg/combined.py
pymic/loss/seg/deep_sup.py
pymic/loss/seg/dice.py
pymic/loss/seg/exp_log.py
pymic/loss/seg/gatedcrf.py
pymic/loss/seg/mse.py
pymic/loss/seg/mumford_shah.py
pymic/loss/seg/slsr.py
pymic/loss/seg/ssl.py
pymic/loss/seg/util.py
pymic/net/__init__.py
pymic/net/multi_net.py
pymic/net/net_dict_cls.py
pymic/net/net_dict_seg.py
pymic/net/net_init.py
pymic/net/cls/__init__.py
pymic/net/cls/torch_pretrained_net.py
pymic/net/net2d/__init__.py
pymic/net/net2d/cople_net.py
pymic/net/net2d/scse2d.py
pymic/net/net2d/umamba.py
pymic/net/net2d/unet2d.py
pymic/net/net2d/unet2d_attention.py
pymic/net/net2d/unet2d_canet.py
pymic/net/net2d/unet2d_cct.py
pymic/net/net2d/unet2d_dual_branch.py
pymic/net/net2d/unet2d_mcnet.py
pymic/net/net2d/unet2d_multi_decoder.py
pymic/net/net2d/unet2d_pp.py
pymic/net/net2d/unet2d_scse.py
pymic/net/net2d/unet2d_vm.py
pymic/net/net2d/unet2d_vm_light.py
pymic/net/net2d/trans2d/__init__.py
pymic/net/net2d/trans2d/swinunet.py
pymic/net/net2d/trans2d/swinunet_sys.py
pymic/net/net2d/trans2d/transunet.py
pymic/net/net2d/trans2d/transunet_cfg.py
pymic/net/net2d/trans2d/transunet_resnet.py
pymic/net/net3d/__init__.py
pymic/net/net3d/fmunet.py
pymic/net/net3d/fmunetv3.py
pymic/net/net3d/grunet.py
pymic/net/net3d/lcovnet.py
pymic/net/net3d/scse3d.py
pymic/net/net3d/unet2d5.py
pymic/net/net3d/unet3d.py
pymic/net/net3d/unet3d_dual_branch.py
pymic/net/net3d/unet3d_scse.py
pymic/net/net3d/trans3d/__init__.py
pymic-0.5.4.dist-info/licenses/LICENSE
pymic-0.5.4.dist-info/METADATA
pymic-0.5.4.dist-info/WHEEL
pymic-0.5.4.dist-info/entry_points.txt
pymic-0.5.4.dist-info/top_level.txt
pymic-0.5.4.dist-info/RECORD
