Metadata-Version: 2.4
Name: PYMIC
Version: 0.5.4
Summary: An open-source deep learning platform for annotation-efficient medical image computing
Home-page: https://github.com/HiLab-git/PyMIC
Author: PyMIC Consortium
Author-email: wguotai@gmail.com
License: Apache 2.0
Classifier: License :: OSI Approved :: Apache Software License
Classifier: Programming Language :: Python
Classifier: Programming Language :: Python :: 2
Classifier: Programming Language :: Python :: 3
Requires-Python: >=3.6
License-File: LICENSE
Requires-Dist: h5py
Requires-Dist: matplotlib>=3.1.2
Requires-Dist: numpy>=1.17.4
Requires-Dist: pandas>=0.25.3
Requires-Dist: scikit-image>=0.16.2
Requires-Dist: scikit-learn>=0.22
Requires-Dist: scipy>=1.3.3
Requires-Dist: SimpleITK>=2.0.0
Requires-Dist: tensorboard
Requires-Dist: tensorboardX
Dynamic: author
Dynamic: author-email
Dynamic: classifier
Dynamic: description
Dynamic: description-content-type
Dynamic: home-page
Dynamic: license
Dynamic: license-file
Dynamic: requires-dist
Dynamic: requires-python
Dynamic: summary
